{"Api.tag":"null/车辆维修保养","getById":{},"deleteById":{"ApiOperation.value":"删除车辆维修保养","ApiImplicitParam.LeMaintenanceVOMeta.ID.name":"主键"},"save":{"ApiImplicitParam.LeMaintenanceVOMeta.ORIGINATOR_ID.name":"制单人","ApiImplicitParam.LeMaintenanceVOMeta.STATUS.name":"办理状态","ApiImplicitParam.LeMaintenanceVOMeta.PROC_ID.name":"流程","ApiImplicitParam.LeMaintenanceVOMeta.NAME.name":"业务名称","ApiOperation.value":"保存车辆维修保养","ApiImplicitParam.LeMaintenanceVOMeta.TYPE.name":"报修类型","ApiImplicitParam.LeMaintenanceVOMeta.COST.name":"费用","ApiImplicitParam.LeMaintenanceVOMeta.CONTENT.name":"报修内容","ApiImplicitParam.LeMaintenanceVOMeta.BUSINESS_DATE.name":"业务日期","ApiImplicitParam.LeMaintenanceVOMeta.PICTURE_ID.name":"图片","ApiImplicitParam.LeMaintenanceVOMeta.SELECTED_CODE.name":"选择数据","ApiImplicitParam.LeMaintenanceVOMeta.ACTUAL_FINISH_DATE.name":"实际完成日期","ApiImplicitParam.LeMaintenanceVOMeta.BUSINESS_CODE.name":"业务编号","ApiImplicitParam.LeMaintenanceVOMeta.REPAIR_STATUS.name":"维修状态","ApiImplicitParam.LeMaintenanceVOMeta.REPORT_USER_ID.name":"报修人","ApiImplicitParam.LeMaintenanceVOMeta.ID.name":"主键","ApiImplicitParam.LeMaintenanceVOMeta.PLAN_FINISH_DATE.name":"计划完成日期","ApiImplicitParam.LeMaintenanceVOMeta.REPORT_USER_NAME.name":"报修人"},"insert":{"ApiImplicitParam.LeMaintenanceVOMeta.ORIGINATOR_ID.name":"制单人","ApiImplicitParam.LeMaintenanceVOMeta.STATUS.name":"办理状态","ApiImplicitParam.LeMaintenanceVOMeta.PROC_ID.name":"流程","ApiImplicitParam.LeMaintenanceVOMeta.NAME.name":"业务名称","ApiOperation.value":"添加车辆维修保养","ApiImplicitParam.LeMaintenanceVOMeta.TYPE.name":"报修类型","ApiImplicitParam.LeMaintenanceVOMeta.COST.name":"费用","ApiImplicitParam.LeMaintenanceVOMeta.CONTENT.name":"报修内容","ApiImplicitParam.LeMaintenanceVOMeta.BUSINESS_DATE.name":"业务日期","ApiImplicitParam.LeMaintenanceVOMeta.PICTURE_ID.name":"图片","ApiImplicitParam.LeMaintenanceVOMeta.SELECTED_CODE.name":"选择数据","ApiImplicitParam.LeMaintenanceVOMeta.ACTUAL_FINISH_DATE.name":"实际完成日期","ApiImplicitParam.LeMaintenanceVOMeta.BUSINESS_CODE.name":"业务编号","ApiImplicitParam.LeMaintenanceVOMeta.REPAIR_STATUS.name":"维修状态","ApiImplicitParam.LeMaintenanceVOMeta.REPORT_USER_ID.name":"报修人","ApiImplicitParam.LeMaintenanceVOMeta.ID.name":"主键","ApiImplicitParam.LeMaintenanceVOMeta.PLAN_FINISH_DATE.name":"计划完成日期","ApiImplicitParam.LeMaintenanceVOMeta.REPORT_USER_NAME.name":"报修人"},"update":{"ApiImplicitParam.LeMaintenanceVOMeta.ORIGINATOR_ID.name":"制单人","ApiImplicitParam.LeMaintenanceVOMeta.STATUS.name":"办理状态","ApiImplicitParam.LeMaintenanceVOMeta.PROC_ID.name":"流程","ApiImplicitParam.LeMaintenanceVOMeta.NAME.name":"业务名称","ApiOperation.value":"更新车辆维修保养","ApiImplicitParam.LeMaintenanceVOMeta.TYPE.name":"报修类型","ApiImplicitParam.LeMaintenanceVOMeta.COST.name":"费用","ApiImplicitParam.LeMaintenanceVOMeta.CONTENT.name":"报修内容","ApiImplicitParam.LeMaintenanceVOMeta.BUSINESS_DATE.name":"业务日期","ApiImplicitParam.LeMaintenanceVOMeta.PICTURE_ID.name":"图片","ApiImplicitParam.LeMaintenanceVOMeta.SELECTED_CODE.name":"选择数据","ApiImplicitParam.LeMaintenanceVOMeta.ACTUAL_FINISH_DATE.name":"实际完成日期","ApiImplicitParam.LeMaintenanceVOMeta.BUSINESS_CODE.name":"业务编号","ApiImplicitParam.LeMaintenanceVOMeta.REPAIR_STATUS.name":"维修状态","ApiImplicitParam.LeMaintenanceVOMeta.REPORT_USER_ID.name":"报修人","ApiImplicitParam.LeMaintenanceVOMeta.ID.name":"主键","ApiImplicitParam.LeMaintenanceVOMeta.PLAN_FINISH_DATE.name":"计划完成日期","ApiImplicitParam.LeMaintenanceVOMeta.REPORT_USER_NAME.name":"报修人"},"queryPagedList":{"ApiImplicitParam.LeMaintenanceVOMeta.ORIGINATOR_ID.name":"制单人","ApiImplicitParam.LeMaintenanceVOMeta.STATUS.name":"办理状态","ApiImplicitParam.LeMaintenanceVOMeta.PROC_ID.name":"流程","ApiImplicitParam.LeMaintenanceVOMeta.NAME.name":"业务名称","ApiOperation.value":"分页查询车辆维修保养","ApiImplicitParam.LeMaintenanceVOMeta.TYPE.name":"报修类型","ApiImplicitParam.LeMaintenanceVOMeta.COST.name":"费用","ApiImplicitParam.LeMaintenanceVOMeta.CONTENT.name":"报修内容","ApiImplicitParam.LeMaintenanceVOMeta.BUSINESS_DATE.name":"业务日期","ApiImplicitParam.LeMaintenanceVOMeta.PICTURE_ID.name":"图片","ApiImplicitParam.LeMaintenanceVOMeta.SELECTED_CODE.name":"选择数据","ApiImplicitParam.LeMaintenanceVOMeta.ACTUAL_FINISH_DATE.name":"实际完成日期","ApiImplicitParam.LeMaintenanceVOMeta.BUSINESS_CODE.name":"业务编号","ApiImplicitParam.LeMaintenanceVOMeta.REPAIR_STATUS.name":"维修状态","ApiImplicitParam.LeMaintenanceVOMeta.REPORT_USER_ID.name":"报修人","ApiImplicitParam.LeMaintenanceVOMeta.ID.name":"主键","ApiImplicitParam.LeMaintenanceVOMeta.PLAN_FINISH_DATE.name":"计划完成日期","ApiImplicitParam.LeMaintenanceVOMeta.REPORT_USER_NAME.name":"报修人"},"queryList":{"ApiImplicitParam.LeMaintenanceVOMeta.ORIGINATOR_ID.name":"制单人","ApiImplicitParam.LeMaintenanceVOMeta.STATUS.name":"办理状态","ApiImplicitParam.LeMaintenanceVOMeta.PROC_ID.name":"流程","ApiImplicitParam.LeMaintenanceVOMeta.NAME.name":"业务名称","ApiOperation.value":"查询车辆维修保养","ApiImplicitParam.LeMaintenanceVOMeta.TYPE.name":"报修类型","ApiImplicitParam.LeMaintenanceVOMeta.COST.name":"费用","ApiImplicitParam.LeMaintenanceVOMeta.CONTENT.name":"报修内容","ApiImplicitParam.LeMaintenanceVOMeta.BUSINESS_DATE.name":"业务日期","ApiImplicitParam.LeMaintenanceVOMeta.PICTURE_ID.name":"图片","ApiImplicitParam.LeMaintenanceVOMeta.SELECTED_CODE.name":"选择数据","ApiImplicitParam.LeMaintenanceVOMeta.ACTUAL_FINISH_DATE.name":"实际完成日期","ApiImplicitParam.LeMaintenanceVOMeta.BUSINESS_CODE.name":"业务编号","ApiImplicitParam.LeMaintenanceVOMeta.REPAIR_STATUS.name":"维修状态","ApiImplicitParam.LeMaintenanceVOMeta.REPORT_USER_ID.name":"报修人","ApiImplicitParam.LeMaintenanceVOMeta.ID.name":"主键","ApiImplicitParam.LeMaintenanceVOMeta.PLAN_FINISH_DATE.name":"计划完成日期","ApiImplicitParam.LeMaintenanceVOMeta.REPORT_USER_NAME.name":"报修人"}}