{"Api.tag":"null/执行介质","getById":{},"deleteById":{"ApiOperation.value":"删除执行介质","ApiImplicitParam.AutoActionFileVOMeta.ID.name":"主键"},"save":{"ApiImplicitParam.AutoActionFileVOMeta.NAME.name":"名称","ApiOperation.value":"保存执行介质","ApiImplicitParam.AutoActionFileVOMeta.FILE_NAME.name":"文件名称","ApiImplicitParam.AutoActionFileVOMeta.NOTES.name":"备注","ApiImplicitParam.AutoActionFileVOMeta.ID.name":"主键","ApiImplicitParam.AutoActionFileVOMeta.FILE_ID.name":"文件"},"insert":{"ApiImplicitParam.AutoActionFileVOMeta.NAME.name":"名称","ApiOperation.value":"添加执行介质","ApiImplicitParam.AutoActionFileVOMeta.FILE_NAME.name":"文件名称","ApiImplicitParam.AutoActionFileVOMeta.NOTES.name":"备注","ApiImplicitParam.AutoActionFileVOMeta.ID.name":"主键","ApiImplicitParam.AutoActionFileVOMeta.FILE_ID.name":"文件"},"update":{"ApiImplicitParam.AutoActionFileVOMeta.NAME.name":"名称","ApiOperation.value":"更新执行介质","ApiImplicitParam.AutoActionFileVOMeta.FILE_NAME.name":"文件名称","ApiImplicitParam.AutoActionFileVOMeta.NOTES.name":"备注","ApiImplicitParam.AutoActionFileVOMeta.ID.name":"主键","ApiImplicitParam.AutoActionFileVOMeta.FILE_ID.name":"文件"},"queryPagedList":{"ApiImplicitParam.AutoActionFileVOMeta.NAME.name":"名称","ApiOperation.value":"分页查询执行介质","ApiImplicitParam.AutoActionFileVOMeta.FILE_NAME.name":"文件名称","ApiImplicitParam.AutoActionFileVOMeta.NOTES.name":"备注","ApiImplicitParam.AutoActionFileVOMeta.ID.name":"主键","ApiImplicitParam.AutoActionFileVOMeta.FILE_ID.name":"文件"},"queryList":{"ApiImplicitParam.AutoActionFileVOMeta.NAME.name":"名称","ApiOperation.value":"查询执行介质","ApiImplicitParam.AutoActionFileVOMeta.FILE_NAME.name":"文件名称","ApiImplicitParam.AutoActionFileVOMeta.NOTES.name":"备注","ApiImplicitParam.AutoActionFileVOMeta.ID.name":"主键","ApiImplicitParam.AutoActionFileVOMeta.FILE_ID.name":"文件"}}